{
    "songNumber": 166,
    "title": "Среде силна бура плови",
    "verses": [
        {
            "content": {
                "lines": [
                    "Среде силна бура плови",
                    "Еден чамец, глеј,",
                    "Виорот го страшен бие,",
                    "Да го потопи."
                ],
                "refrain": false
            }
        },
        {
            "content": {
                "lines": [
                    "Храбро, само напред,",
                    "Чујте Христов глас:",
                    "“Јас сум со вас в сите деној,",
                    "Од смртта ќе ве спасам вас!",
                    "Да, јас сум со вас в сите деној,",
                    "Од смртта ќе ве спасам вас!”"
                ],
                "refrain": true
            }
        },
        {
            "content": {
                "lines": [
                    "Глеј бродарите се в умор,",
                    "Немоќни се, знај,",
                    "И го молат Спасот сега",
                    "Да ги избави."
                ],
                "refrain": false
            }
        },
        {
            "content": {
                "lines": [
                    "Кога в твојот живот клоне",
                    "Надеж, вера, сè,",
                    "Чуј го твојот Спас, о чуј го:",
                    "“Веруј, веруј ти!”"
                ],
                "refrain": false
            }
        },
        {
            "content": {
                "lines": [
                    "Да те спаси Тој од смртта,",
                    "Еднаш умре знај,",
                    "Појди смело појди напред,",
                    "Тој те води в рај."
                ],
                "refrain": false
            }
        }
    ]
}