{
    "songNumber": 128,
    "title": "Твојот крај, твојот крај",
    "verses": [
        {
            "content": {
                "lines": [
                    "Твојот крај, твојот крај",
                    "Е мој вечен рај,",
                    "О колку мил е твојот крај",
                    "И мил е твојот дом.",
                    "На овој свет сум гостин јас,",
                    "За тоа добро знам,",
                    "За твојот дом јас копнеам,",
                    "О мили Спасе мој."
                ],
                "refrain": false
            }
        },
        {
            "content": {
                "lines": [
                    "Твојот крај, твојот крај",
                    "Е мој вечен рај,",
                    "О колку мил е твојот крај",
                    "И мил е твојот дом."
                ],
                "refrain": true
            }
        },
        {
            "content": {
                "lines": [
                    "Во домот твој, во домот твој",
                    "Дигам поглед свој.",
                    "О колку долго в небо си",
                    "А јас на земјава",
                    "Во борба с гревој секој ден,",
                    "Со страдање и јад.",
                    "Во твојот крај, о гледам јас,",
                    "За него копнеам."
                ],
                "refrain": false
            }
        },
        {
            "content": {
                "lines": [
                    "Близу е, близу е,",
                    "Близу е тој час,",
                    "Ќе појдам и јас в домот свој,",
                    "Во вечен мир и спас.",
                    "Што уште никој не видел",
                    "Ни чул до овој час,",
                    "Ни готви Бог, јас добро знам,",
                    "Наш Господ, Бог е Спас."
                ],
                "refrain": false
            }
        }
    ]
}